README.rst
setup.py
mtd/__init__.py
mtd/design.py
mtd.egg-info/PKG-INFO
mtd.egg-info/SOURCES.txt
mtd.egg-info/dependency_links.txt
mtd.egg-info/requires.txt
mtd.egg-info/top_level.txt
mtd/test/__init__.py
mtd/test/test_design.py